zangetsu_logger/__init__.py
zangetsu_logger/cloud_handlers.py
zangetsu_logger/config.py
zangetsu_logger/default_config.yaml
zangetsu_logger/formatters.py
zangetsu_logger/handlers.py
zangetsu_logger-0.1.1.dist-info/METADATA
zangetsu_logger-0.1.1.dist-info/WHEEL
zangetsu_logger-0.1.1.dist-info/top_level.txt
zangetsu_logger-0.1.1.dist-info/RECORD
