Metadata-Version: 2.2
Name: zangetsu-logger
Version: 0.1.1
Summary: Add your description here
Requires-Python: >=3.11
Requires-Dist: boto3>=1.37.9
Requires-Dist: google-cloud-storage>=3.1.0
Requires-Dist: python-json-logger>=3.2.1
Requires-Dist: pytz>=2025.1
Requires-Dist: pyyaml>=6.0.2
